{"data":{"refreshInterval":0,"game":{"awayteamid":1,"awayteamname":"New Jersey Devils","hometeamname":"Tampa Bay Lightning","plays":{"play":[{"sweater":"12","localtime":"7:38 PM","xcoord":-14,"desc":"Simon Gagne HIT on David Clarkson","teamid":14,"strength":701,"pid":8467346,"formalEventId":"T.B51","period":1,"type":"Hit","p3name":"","eventid":51,"p2name":"David Clarkson","ycoord":35,"pid3":"","time":"00:10","playername":"Simon Gagne","p1name":"Simon Gagne","pid2":8470920,"pid1":8467346},{"sweater":"10","localtime":"7:38 PM","xcoord":-65,"desc":"Rod Pelley SHOT on Dwayne Roloson","teamid":1,"strength":701,"pid":8472355,"formalEventId":"T.B7","period":1,"type":"Shot","p3name":"","eventid":7,"p2name":"Dwayne Roloson","ycoord":-30,"pid3":"","time":"00:09","playername":"Rod Pelley","p1name":"Rod Pelley","pid2":8460806,"pid1":8472355},{"sweater":"5","localtime":"7:39 PM","xcoord":44,"desc":"Mattias Ohlund HIT on Nick Palmieri","teamid":14,"strength":701,"pid":8460503,"formalEventId":"T.B53","period":1,"type":"Hit","p3name":"","eventid":53,"p2name":"Nick Palmieri","ycoord":38,"pid3":"","time":"00:30","playername":"Mattias Ohlund","p1name":"Mattias Ohlund","pid2":8473999,"pid1":8460503},{"sweater":"5","localtime":"7:39 PM","xcoord":-8,"desc":"Colin White SHOT on Dwayne Roloson","teamid":1,"strength":701,"pid":8465005,"formalEventId":"T.B9","period":1,"type":"Shot","p3name":"","eventid":9,"p2name":"Dwayne Roloson","ycoord":-36,"pid3":"","time":"00:55","playername":"Colin White","p1name":"Colin White","pid2":8460806,"pid1":8465005},{"sweater":"12","localtime":"7:40 PM","xcoord":-87,"desc":"Brian Rolston HIT on Ryan Malone","teamid":1,"strength":701,"pid":8458525,"formalEventId":"T.B54","period":1,"type":"Hit","p3name":"","eventid":54,"p2name":"Ryan Malone","ycoord":-30,"pid3":"","time":"01:11","playername":"Brian Rolston","p1name":"Brian Rolston","pid2":8467988,"pid1":8458525},{"sweater":"6","localtime":"7:40 PM","xcoord":-5,"desc":"Ryan Malone HIT on Colin White","teamid":14,"strength":701,"pid":8467988,"formalEventId":"T.B55","period":1,"type":"Hit","p3name":"","eventid":55,"p2name":"Colin White","ycoord":-40,"pid3":"","time":"01:18","playername":"Ryan Malone","p1name":"Ryan Malone","pid2":8465005,"pid1":8467988},{"sweater":"6","localtime":"7:40 PM","xcoord":-93,"desc":"Ryan Malone HIT on Henrik Tallinder","teamid":14,"strength":701,"pid":8467988,"formalEventId":"T.B56","period":1,"type":"Hit","p3name":"","eventid":56,"p2name":"Henrik Tallinder","ycoord":-9,"pid3":"","time":"01:23","playername":"Ryan Malone","p1name":"Ryan Malone","pid2":8466182,"pid1":8467988},{"sweater":"23","localtime":"7:42 PM","xcoord":-94,"desc":"David Clarkson HIT on Victor Hedman","teamid":1,"strength":701,"pid":8470920,"formalEventId":"T.B58","period":1,"type":"Hit","p3name":"","eventid":58,"p2name":"Victor Hedman","ycoord":-31,"pid3":"","time":"03:07","playername":"David Clarkson","p1name":"David Clarkson","pid2":8475167,"pid1":8470920},{"sweater":"42","localtime":"7:42 PM","xcoord":-11,"desc":"Dana Tyrell HIT on Mark Fayne","teamid":14,"strength":701,"pid":8474095,"formalEventId":"T.B59","period":1,"type":"Hit","p3name":"","eventid":59,"p2name":"Mark Fayne","ycoord":36,"pid3":"","time":"03:31","playername":"Dana Tyrell","p1name":"Dana Tyrell","pid2":8471816,"pid1":8474095},{"sweater":"26","localtime":"7:44 PM","xcoord":-45,"desc":"Patrik Elias SHOT on Dwayne Roloson","teamid":1,"strength":701,"pid":8460542,"formalEventId":"T.B18","period":1,"type":"Shot","p3name":"","eventid":18,"p2name":"Dwayne Roloson","ycoord":-28,"pid3":"","time":"04:40","playername":"Patrik Elias","p1name":"Patrik Elias","pid2":8460806,"pid1":8460542},{"sweater":"18","localtime":"7:44 PM","xcoord":-49,"desc":"Adam Hall HIT on Brian Rolston","teamid":14,"strength":701,"pid":8467925,"formalEventId":"T.B63","period":1,"type":"Hit","p3name":"","eventid":63,"p2name":"Brian Rolston","ycoord":1,"pid3":"","time":"04:42","playername":"Adam Hall","p1name":"Adam Hall","pid2":8458525,"pid1":8467925},{"sweater":"5","localtime":"7:45 PM","xcoord":62,"desc":"Colin White HI-STICKING on Steven Stamkos","teamid":1,"strength":703,"pid":8465005,"formalEventId":"T.B64","period":1,"type":"Penalty","p3name":"","eventid":64,"p2name":"Steven Stamkos","ycoord":2,"pid3":"","time":"04:56","playername":"Colin White","p1name":"Colin White","pid2":8474564,"pid1":8465005},{"sweater":"91","altVideo":"http://h264.nhl.com/20102011/02/0658/2_658_njd_tbl_1011_a_discrete_T.B21_goal_800K_16x9_2.mp4","desc":"Steven Stamkos GOAL on Martin Brodeur","g_shotType":"Slap Shot","formalEventId":"T.B21","type":"Goal","eventid":21,"g_totes":32,"p2name":"Martin Brodeur","time":"05:06","g_goalie":"Brodeur, M.","video":"2_658_njd_tbl_1011_a_discrete_T.B21_goal_800K_16x9_2.flv","g_ass2totes":13,"localtime":"7:46 PM","assists":"M. St Louis (36), V. Lecavalier (13)","teamid":14,"xcoord":75,"strength":702,"g_goalieID":8455710,"pid":8474564,"period":1,"g_ass1totes":36,"p3name":"Vincent Lecavalier","pid3":8467329,"ycoord":20,"playername":"Steven Stamkos","p1name":"Steven Stamkos","pid2":8455710,"pid1":8474564},{"sweater":"14","localtime":"7:47 PM","xcoord":93,"desc":"Tim Sestito HIT on Steve Downie","teamid":1,"strength":701,"pid":8471636,"formalEventId":"T.B67","period":1,"type":"Hit","p3name":"","eventid":67,"p2name":"Steve Downie","ycoord":-23,"pid3":"","time":"05:39","playername":"Tim Sestito","p1name":"Tim Sestito","pid2":8471703,"pid1":8471636},{"sweater":"8","localtime":"7:47 PM","xcoord":34,"desc":"Randy Jones SHOT on Martin Brodeur","teamid":14,"strength":701,"pid":8470905,"formalEventId":"T.B24","period":1,"type":"Shot","p3name":"","eventid":24,"p2name":"Martin Brodeur","ycoord":21,"pid3":"","time":"05:44","playername":"Randy Jones","p1name":"Randy Jones","pid2":8455710,"pid1":8470905},{"altVideo":"http://h264.nhl.com/20102011/02/0658/2_658_njd_tbl_1011_a_discrete_T.B25_save_800K_16x9_2.mp4","sweater":"23","localtime":"7:47 PM","xcoord":-61,"desc":"David Clarkson SHOT on Dwayne Roloson","teamid":1,"strength":701,"pid":8470920,"formalEventId":"T.B25","period":1,"type":"Shot","p3name":"","eventid":25,"p2name":"Dwayne Roloson","ycoord":9,"pid3":"","time":"05:59","playername":"David Clarkson","p1name":"David Clarkson","video":"2_658_njd_tbl_1011_a_discrete_T.B25_save_800K_16x9_2.flv","pid2":8460806,"pid1":8470920},{"sweater":"7","localtime":"7:48 PM","xcoord":-22,"desc":"Brett Clark HIT on Vladimir Zharkov","teamid":14,"strength":701,"pid":8465122,"formalEventId":"T.B69","period":1,"type":"Hit","p3name":"","eventid":69,"p2name":"Vladimir Zharkov","ycoord":28,"pid3":"","time":"06:22","playername":"Brett Clark","p1name":"Brett Clark","pid2":8473592,"pid1":8465122},{"sweater":"17","altVideo":"http://h264.nhl.com/20102011/02/0658/2_658_njd_tbl_1011_a_discrete_T.B27_goal_800K_16x9_2.mp4","desc":"Ilya Kovalchuk GOAL on Dwayne Roloson","g_shotType":"Wrist Shot","formalEventId":"T.B27","type":"Goal","eventid":27,"g_totes":11,"p2name":"Dwayne Roloson","time":"07:59","g_goalie":"Roloson, D.","video":"2_658_njd_tbl_1011_h_discrete_T.B27_goal_800K_16x9_2.flv","g_ass2totes":11,"localtime":"7:49 PM","assists":"T. Zajac (16), A. Greene (11)","teamid":1,"xcoord":-52,"strength":701,"g_goalieID":8460806,"pid":8469454,"period":1,"g_ass1totes":16,"p3name":"Andy Greene","pid3":8472382,"ycoord":-1,"playername":"Ilya Kovalchuk","p1name":"Ilya Kovalchuk","pid2":8460806,"pid1":8469454},{"sweater":"12","altVideo":"http://h264.nhl.com/20102011/02/0658/2_658_njd_tbl_1011_a_discrete_T.B29_goal_800K_16x9_2.mp4","desc":"Brian Rolston GOAL on Dwayne Roloson","g_shotType":"Slap Shot","formalEventId":"T.B29","type":"Goal","eventid":29,"g_totes":3,"p2name":"Dwayne Roloson","time":"09:19","g_goalie":"Roloson, D.","video":"2_658_njd_tbl_1011_a_discrete_T.B29_goal_800K_16x9_2.flv","localtime":"7:51 PM","assists":"D. Zubrus (10)","teamid":1,"xcoord":-64,"strength":701,"g_goalieID":8460806,"pid":8458525,"period":1,"g_ass1totes":10,"p3name":"","pid3":"","ycoord":8,"playername":"Brian Rolston","p1name":"Brian Rolston","pid2":8460806,"pid1":8458525},{"sweater":"77","localtime":"7:56 PM","xcoord":-29,"desc":"Victor Hedman HIT on Rod Pelley","teamid":14,"strength":701,"pid":8475167,"formalEventId":"T.B74","period":1,"type":"Hit","p3name":"","eventid":74,"p2name":"Rod Pelley","ycoord":38,"pid3":"","time":"10:50","playername":"Victor Hedman","p1name":"Victor Hedman","pid2":8472355,"pid1":8475167},{"sweater":"2","localtime":"7:57 PM","xcoord":82,"desc":"Mark Fraser HIT on Teddy Purcell","teamid":1,"strength":701,"pid":8471748,"formalEventId":"T.B75","period":1,"type":"Hit","p3name":"","eventid":75,"p2name":"Teddy Purcell","ycoord":-34,"pid3":"","time":"11:05","playername":"Mark Fraser","p1name":"Mark Fraser","pid2":8473962,"pid1":8471748},{"sweater":"12","localtime":"7:57 PM","xcoord":74,"desc":"Simon Gagne SHOT on Martin Brodeur","teamid":14,"strength":701,"pid":8467346,"formalEventId":"T.B35","period":1,"type":"Shot","p3name":"","eventid":35,"p2name":"Martin Brodeur","ycoord":-5,"pid3":"","time":"11:36","playername":"Simon Gagne","p1name":"Simon Gagne","pid2":8455710,"pid1":8467346},{"sweater":"6","localtime":"7:57 PM","xcoord":-73,"desc":"Andy Greene SHOT on Dwayne Roloson","teamid":1,"strength":701,"pid":8472382,"formalEventId":"T.B36","period":1,"type":"Shot","p3name":"","eventid":36,"p2name":"Dwayne Roloson","ycoord":-6,"pid3":"","time":"11:41","playername":"Andy Greene","p1name":"Andy Greene","pid2":8460806,"pid1":8472382},{"sweater":"26","altVideo":"http://h264.nhl.com/20102011/02/0658/2_658_njd_tbl_1011_a_discrete_T.B37_goal_800K_16x9_2.mp4","desc":"Patrik Elias GOAL on Dwayne Roloson","g_shotType":"Slap Shot","formalEventId":"T.B37","type":"Goal","eventid":37,"g_totes":10,"p2name":"Dwayne Roloson","time":"11:44","g_goalie":"Roloson, D.","video":"2_658_njd_tbl_1011_h_discrete_T.B37_goal_800K_16x9_3.flv","g_ass2totes":6,"localtime":"7:58 PM","assists":"A. Greene (12), B. Rolston (6)","teamid":1,"xcoord":-69,"strength":701,"g_goalieID":8460806,"pid":8460542,"period":1,"g_ass1totes":12,"p3name":"Brian Rolston","pid3":8458525,"ycoord":-12,"playername":"Patrik Elias","p1name":"Patrik Elias","pid2":8460806,"pid1":8460542},{"sweater":"18","localtime":"7:59 PM","xcoord":57,"desc":"Adam Hall SHOT on Martin Brodeur","teamid":14,"strength":701,"pid":8467925,"formalEventId":"T.B40","period":1,"type":"Shot","p3name":"","eventid":40,"p2name":"Martin Brodeur","ycoord":-30,"pid3":"","time":"12:18","playername":"Adam Hall","p1name":"Adam Hall","pid2":8455710,"pid1":8467925},{"sweater":"5","localtime":"8:00 PM","xcoord":35,"desc":"Mattias Ohlund SHOT on Martin Brodeur","teamid":14,"strength":701,"pid":8460503,"formalEventId":"T.B41","period":1,"type":"Shot","p3name":"","eventid":41,"p2name":"Martin Brodeur","ycoord":31,"pid3":"","time":"12:25","playername":"Mattias Ohlund","p1name":"Mattias Ohlund","pid2":8455710,"pid1":8460503},{"sweater":"91","localtime":"8:01 PM","xcoord":72,"desc":"Steven Stamkos SHOT on Martin Brodeur","teamid":14,"strength":701,"pid":8474564,"formalEventId":"T.B43","period":1,"type":"Shot","p3name":"","eventid":43,"p2name":"Martin Brodeur","ycoord":4,"pid3":"","time":"13:30","playername":"Steven Stamkos","p1name":"Steven Stamkos","pid2":8455710,"pid1":8474564},{"sweater":"9","localtime":"8:01 PM","xcoord":-12,"desc":"Steve Downie FIGHTING (MAJ) on Matthew Corrente","teamid":14,"strength":703,"pid":8471703,"formalEventId":"T.B78","period":1,"type":"Fight","p3name":"","eventid":78,"p2name":"Matthew Corrente","ycoord":-1,"pid3":"","time":"13:38","playername":"Steve Downie","p1name":"Steve Downie","pid2":8473580,"pid1":8471703},{"sweater":"22","localtime":"8:02 PM","xcoord":-22,"desc":"Matthew Corrente FIGHTING (MAJ) on Steve Downie","teamid":1,"strength":701,"pid":8473580,"formalEventId":"T.B80","period":1,"type":"Fight","p3name":"","eventid":80,"p2name":"Steve Downie","ycoord":-3,"pid3":"","time":"13:38","playername":"Matthew Corrente","p1name":"Matthew Corrente","pid2":8471703,"pid1":8473580},{"sweater":"12","localtime":"8:04 PM","xcoord":-42,"desc":"Simon Gagne HIT on Henrik Tallinder","teamid":14,"strength":701,"pid":8467346,"formalEventId":"T.B83","period":1,"type":"Hit","p3name":"","eventid":83,"p2name":"Henrik Tallinder","ycoord":33,"pid3":"","time":"13:45","playername":"Simon Gagne","p1name":"Simon Gagne","pid2":8466182,"pid1":8467346},{"sweater":"77","localtime":"8:04 PM","xcoord":39,"desc":"Victor Hedman SHOT on Martin Brodeur","teamid":14,"strength":701,"pid":8475167,"formalEventId":"T.B45","period":1,"type":"Shot","p3name":"","eventid":45,"p2name":"Martin Brodeur","ycoord":23,"pid3":"","time":"14:10","playername":"Victor Hedman","p1name":"Victor Hedman","pid2":8455710,"pid1":8475167},{"sweater":"10","localtime":"8:06 PM","xcoord":-80,"desc":"Rod Pelley HI-STICKING on Victor Hedman","teamid":1,"strength":703,"pid":8472355,"formalEventId":"T.B87","period":1,"type":"Penalty","p3name":"","eventid":87,"p2name":"Victor Hedman","ycoord":-30,"pid3":"","time":"15:12","playername":"Rod Pelley","p1name":"Rod Pelley","pid2":8475167,"pid1":8472355},{"sweater":"5","localtime":"8:09 PM","xcoord":40,"desc":"Colin White HIT on Vincent Lecavalier","teamid":1,"strength":703,"pid":8465005,"formalEventId":"T.B89","period":1,"type":"Hit","p3name":"","eventid":89,"p2name":"Vincent Lecavalier","ycoord":-30,"pid3":"","time":"15:33","playername":"Colin White","p1name":"Colin White","pid2":8467329,"pid1":8465005},{"sweater":"19","altVideo":"http://h264.nhl.com/20102011/02/0658/2_658_njd_tbl_1011_a_discrete_T.B48_goal_800K_16x9_1.mp4","desc":"Travis Zajac GOAL on Dwayne Roloson","g_shotType":"Wrist Shot","formalEventId":"T.B48","type":"Goal","eventid":48,"g_totes":7,"p2name":"Dwayne Roloson","time":"15:54","g_goalie":"Roloson, D.","video":"2_658_njd_tbl_1011_h_ingame_T.B48_goal_800K_16x9_2.flv","localtime":"8:09 PM","assists":"C. White (2)","teamid":1,"xcoord":-61,"strength":703,"g_goalieID":8460806,"pid":8471233,"period":1,"g_ass1totes":2,"p3name":"","pid3":"","ycoord":2,"playername":"Travis Zajac","p1name":"Travis Zajac","pid2":8460806,"pid1":8471233},{"altVideo":"http://h264.nhl.com/20102011/02/0658/2_658_njd_tbl_1011_a_discrete_T.B701_save_800K_16x9_2.mp4","sweater":"12","localtime":"8:12 PM","xcoord":81,"desc":"Simon Gagne SHOT on Martin Brodeur","teamid":14,"strength":702,"pid":8467346,"formalEventId":"T.B701","period":1,"type":"Shot","p3name":"","eventid":701,"p2name":"Martin Brodeur","ycoord":-15,"pid3":"","time":"17:00","playername":"Simon Gagne","p1name":"Simon Gagne","video":"2_658_njd_tbl_1011_a_discrete_T.B701_save_800K_16x9_2.flv","pid2":8455710,"pid1":8467346},{"sweater":"5","localtime":"8:14 PM","xcoord":94,"desc":"Colin White HIT on Martin St Louis","teamid":1,"strength":701,"pid":8465005,"formalEventId":"T.B92","period":1,"type":"Hit","p3name":"","eventid":92,"p2name":"Martin St Louis","ycoord":-7,"pid3":"","time":"17:34","playername":"Colin White","p1name":"Colin White","pid2":8466378,"pid1":8465005},{"sweater":"44","localtime":"8:16 PM","xcoord":73,"desc":"Nate Thompson HIT on Mark Fayne","teamid":14,"strength":701,"pid":8470775,"formalEventId":"T.B95","period":1,"type":"Hit","p3name":"","eventid":95,"p2name":"Mark Fayne","ycoord":41,"pid3":"","time":"18:25","playername":"Nate Thompson","p1name":"Nate Thompson","pid2":8471816,"pid1":8470775},{"sweater":"19","localtime":"8:16 PM","xcoord":79,"desc":"Dominic Moore SHOT on Martin Brodeur","teamid":14,"strength":701,"pid":8468575,"formalEventId":"T.B707","period":1,"type":"Shot","p3name":"","eventid":707,"p2name":"Martin Brodeur","ycoord":25,"pid3":"","time":"18:49","playername":"Dominic Moore","p1name":"Dominic Moore","pid2":8455710,"pid1":8468575},{"sweater":"10","localtime":"8:36 PM","xcoord":-76,"desc":"Sean Bergenheim SHOT on Martin Brodeur","teamid":14,"strength":701,"pid":8470176,"formalEventId":"T.B718","period":2,"type":"Shot","p3name":"","eventid":718,"p2name":"Martin Brodeur","ycoord":-4,"pid3":"","time":"00:17","playername":"Sean Bergenheim","p1name":"Sean Bergenheim","pid2":8455710,"pid1":8470176},{"sweater":"4","localtime":"8:36 PM","xcoord":-96,"desc":"Vincent Lecavalier HIT on Andy Greene","teamid":14,"strength":701,"pid":8467329,"formalEventId":"T.B98","period":2,"type":"Hit","p3name":"","eventid":98,"p2name":"Andy Greene","ycoord":23,"pid3":"","time":"00:23","playername":"Vincent Lecavalier","p1name":"Vincent Lecavalier","pid2":8472382,"pid1":8467329},{"sweater":"23","localtime":"8:36 PM","xcoord":64,"desc":"David Clarkson SHOT on Dan Ellis","teamid":1,"strength":701,"pid":8470920,"formalEventId":"T.B719","period":2,"type":"Shot","p3name":"","eventid":719,"p2name":"Dan Ellis","ycoord":-19,"pid3":"","time":"00:44","playername":"David Clarkson","p1name":"David Clarkson","pid2":8468540,"pid1":8470920},{"sweater":"25","localtime":"8:37 PM","xcoord":76,"desc":"Jason Arnott SHOT on Dan Ellis","teamid":1,"strength":701,"pid":8459429,"formalEventId":"T.B720","period":2,"type":"Shot","p3name":"","eventid":720,"p2name":"Dan Ellis","ycoord":4,"pid3":"","time":"01:03","playername":"Jason Arnott","p1name":"Jason Arnott","pid2":8468540,"pid1":8459429},{"sweater":"44","localtime":"8:39 PM","xcoord":-23,"desc":"Nate Thompson HIT on Ilya Kovalchuk","teamid":14,"strength":701,"pid":8470775,"formalEventId":"T.B802","period":2,"type":"Hit","p3name":"","eventid":802,"p2name":"Ilya Kovalchuk","ycoord":38,"pid3":"","time":"03:13","playername":"Nate Thompson","p1name":"Nate Thompson","pid2":8469454,"pid1":8470775},{"sweater":"26","localtime":"8:39 PM","xcoord":-45,"desc":"Martin St Louis SHOT on Martin Brodeur","teamid":14,"strength":701,"pid":8466378,"formalEventId":"T.B723","period":2,"type":"Shot","p3name":"","eventid":723,"p2name":"Martin Brodeur","ycoord":-8,"pid3":"","time":"03:54","playername":"Martin St Louis","p1name":"Martin St Louis","pid2":8455710,"pid1":8466378},{"sweater":"4","localtime":"8:41 PM","xcoord":-75,"desc":"Vincent Lecavalier SHOT on Martin Brodeur","teamid":14,"strength":701,"pid":8467329,"formalEventId":"T.B726","period":2,"type":"Shot","p3name":"","eventid":726,"p2name":"Martin Brodeur","ycoord":-5,"pid3":"","time":"04:32","playername":"Vincent Lecavalier","p1name":"Vincent Lecavalier","pid2":8455710,"pid1":8467329},{"altVideo":"http://h264.nhl.com/20102011/02/0658/2_658_njd_tbl_1011_a_discrete_T.B727_save_800K_16x9_1.mp4","sweater":"4","localtime":"8:41 PM","xcoord":-71,"desc":"Vincent Lecavalier SHOT on Martin Brodeur","teamid":14,"strength":701,"pid":8467329,"formalEventId":"T.B727","period":2,"type":"Shot","p3name":"","eventid":727,"p2name":"Martin Brodeur","ycoord":-7,"pid3":"","time":"04:44","playername":"Vincent Lecavalier","p1name":"Vincent Lecavalier","video":"2_658_njd_tbl_1011_a_discrete_T.B727_save_800K_16x9_1.flv","pid2":8455710,"pid1":8467329},{"sweater":"32","localtime":"8:41 PM","xcoord":49,"desc":"Nick Palmieri SHOT on Dan Ellis","teamid":1,"strength":701,"pid":8473999,"formalEventId":"T.B728","period":2,"type":"Shot","p3name":"","eventid":728,"p2name":"Dan Ellis","ycoord":-3,"pid3":"","time":"04:52","playername":"Nick Palmieri","p1name":"Nick Palmieri","pid2":8468540,"pid1":8473999},{"sweater":"19","localtime":"8:42 PM","xcoord":-78,"desc":"Dominic Moore SHOT on Martin Brodeur","teamid":14,"strength":701,"pid":8468575,"formalEventId":"T.B730","period":2,"type":"Shot","p3name":"","eventid":730,"p2name":"Martin Brodeur","ycoord":8,"pid3":"","time":"05:59","playername":"Dominic Moore","p1name":"Dominic Moore","pid2":8455710,"pid1":8468575},{"sweater":"16","localtime":"8:42 PM","xcoord":-58,"desc":"Teddy Purcell SHOT on Martin Brodeur","teamid":14,"strength":701,"pid":8473962,"formalEventId":"T.B731","period":2,"type":"Shot","p3name":"","eventid":731,"p2name":"Martin Brodeur","ycoord":23,"pid3":"","time":"06:14","playername":"Teddy Purcell","p1name":"Teddy Purcell","pid2":8455710,"pid1":8473962},{"sweater":"18","localtime":"8:42 PM","xcoord":-19,"desc":"Adam Hall HIT on Patrik Elias","teamid":14,"strength":701,"pid":8467925,"formalEventId":"T.B808","period":2,"type":"Hit","p3name":"","eventid":808,"p2name":"Patrik Elias","ycoord":-26,"pid3":"","time":"06:23","playername":"Adam Hall","p1name":"Adam Hall","pid2":8460542,"pid1":8467925},{"sweater":"34","localtime":"8:45 PM","xcoord":-68,"desc":"Mark Fayne HIT on Simon Gagne","teamid":1,"strength":701,"pid":8471816,"formalEventId":"T.B810","period":2,"type":"Hit","p3name":"","eventid":810,"p2name":"Simon Gagne","ycoord":39,"pid3":"","time":"07:03","playername":"Mark Fayne","p1name":"Mark Fayne","pid2":8467346,"pid1":8471816},{"sweater":"14","localtime":"8:45 PM","xcoord":41,"desc":"Tim Sestito SHOT on Dan Ellis","teamid":1,"strength":701,"pid":8471636,"formalEventId":"T.B734","period":2,"type":"Shot","p3name":"","eventid":734,"p2name":"Dan Ellis","ycoord":28,"pid3":"","time":"07:10","playername":"Tim Sestito","p1name":"Tim Sestito","pid2":8468540,"pid1":8471636},{"sweater":"25","localtime":"8:46 PM","xcoord":-86,"desc":"Jason Arnott HI-STICKING on Martin St Louis","teamid":1,"strength":703,"pid":8459429,"formalEventId":"T.B812","period":2,"type":"Penalty","p3name":"","eventid":812,"p2name":"Martin St Louis","ycoord":30,"pid3":"","time":"07:35","playername":"Jason Arnott","p1name":"Jason Arnott","pid2":8466378,"pid1":8459429},{"sweater":"12","localtime":"8:47 PM","xcoord":50,"desc":"Brian Rolston SHOT on Dan Ellis","teamid":1,"strength":703,"pid":8458525,"formalEventId":"T.B738","period":2,"type":"Shot","p3name":"","eventid":738,"p2name":"Dan Ellis","ycoord":32,"pid3":"","time":"08:03","playername":"Brian Rolston","p1name":"Brian Rolston","pid2":8468540,"pid1":8458525},{"sweater":"2","localtime":"8:49 PM","xcoord":-93,"desc":"Mark Fraser HIT on Sean Bergenheim","teamid":1,"strength":703,"pid":8471748,"formalEventId":"T.B814","period":2,"type":"Hit","p3name":"","eventid":814,"p2name":"Sean Bergenheim","ycoord":19,"pid3":"","time":"09:20","playername":"Mark Fraser","p1name":"Mark Fraser","pid2":8470176,"pid1":8471748},{"sweater":"25","localtime":"8:50 PM","xcoord":46,"desc":"Jason Arnott SHOT on Dan Ellis","teamid":1,"strength":701,"pid":8459429,"formalEventId":"T.B743","period":2,"type":"Shot","p3name":"","eventid":743,"p2name":"Dan Ellis","ycoord":3,"pid3":"","time":"10:13","playername":"Jason Arnott","p1name":"Jason Arnott","pid2":8468540,"pid1":8459429},{"sweater":"5","localtime":"8:53 PM","xcoord":4,"desc":"Mattias Ohlund HIT on David Clarkson","teamid":14,"strength":701,"pid":8460503,"formalEventId":"T.B818","period":2,"type":"Hit","p3name":"","eventid":818,"p2name":"David Clarkson","ycoord":3,"pid3":"","time":"11:07","playername":"Mattias Ohlund","p1name":"Mattias Ohlund","pid2":8470920,"pid1":8460503},{"sweater":"91","localtime":"8:55 PM","xcoord":-93,"desc":"Steven Stamkos HIT on Colin White","teamid":14,"strength":701,"pid":8474564,"formalEventId":"T.B820","period":2,"type":"Hit","p3name":"","eventid":820,"p2name":"Colin White","ycoord":-8,"pid3":"","time":"12:19","playername":"Steven Stamkos","p1name":"Steven Stamkos","pid2":8465005,"pid1":8474564},{"sweater":"6","localtime":"8:55 PM","xcoord":-81,"desc":"Ryan Malone SHOT on Martin Brodeur","teamid":14,"strength":701,"pid":8467988,"formalEventId":"T.B749","period":2,"type":"Shot","p3name":"","eventid":749,"p2name":"Martin Brodeur","ycoord":-5,"pid3":"","time":"12:20","playername":"Ryan Malone","p1name":"Ryan Malone","pid2":8455710,"pid1":8467988},{"altVideo":"http://h264.nhl.com/20102011/02/0658/2_658_njd_tbl_1011_a_discrete_T.B750_save_800K_16x9_1.mp4","sweater":"13","localtime":"8:55 PM","xcoord":-51,"desc":"Pavel Kubina SHOT on Martin Brodeur","teamid":14,"strength":701,"pid":8465210,"formalEventId":"T.B750","period":2,"type":"Shot","p3name":"","eventid":750,"p2name":"Martin Brodeur","ycoord":33,"pid3":"","time":"12:26","playername":"Pavel Kubina","p1name":"Pavel Kubina","video":"2_658_njd_tbl_1011_a_discrete_T.B750_save_800K_16x9_1.flv","pid2":8455710,"pid1":8465210},{"sweater":"32","localtime":"8:56 PM","xcoord":72,"desc":"Nick Palmieri SHOT on Dan Ellis","teamid":1,"strength":701,"pid":8473999,"formalEventId":"T.B852","period":2,"type":"Shot","p3name":"","eventid":852,"p2name":"Dan Ellis","ycoord":-33,"pid3":"","time":"13:03","playername":"Nick Palmieri","p1name":"Nick Palmieri","pid2":8468540,"pid1":8473999},{"sweater":"2","localtime":"8:56 PM","xcoord":41,"desc":"Mark Fraser SHOT on Dan Ellis","teamid":1,"strength":701,"pid":8471748,"formalEventId":"T.B854","period":2,"type":"Shot","p3name":"","eventid":854,"p2name":"Dan Ellis","ycoord":27,"pid3":"","time":"13:21","playername":"Mark Fraser","p1name":"Mark Fraser","pid2":8468540,"pid1":8471748},{"altVideo":"http://h264.nhl.com/20102011/02/0658/2_658_njd_tbl_1011_a_discrete_T.B856_save_800K_16x9_1.mp4","sweater":"13","localtime":"8:57 PM","xcoord":-34,"desc":"Pavel Kubina SHOT on Martin Brodeur","teamid":14,"strength":701,"pid":8465210,"formalEventId":"T.B856","period":2,"type":"Shot","p3name":"","eventid":856,"p2name":"Martin Brodeur","ycoord":7,"pid3":"","time":"13:38","playername":"Pavel Kubina","p1name":"Pavel Kubina","video":"2_658_njd_tbl_1011_a_discrete_T.B856_save_800K_16x9_1.flv","pid2":8455710,"pid1":8465210},{"sweater":"18","localtime":"8:58 PM","xcoord":-87,"desc":"Adam Hall HIT on Travis Zajac","teamid":14,"strength":701,"pid":8467925,"formalEventId":"T.B824","period":2,"type":"Hit","p3name":"","eventid":824,"p2name":"Travis Zajac","ycoord":35,"pid3":"","time":"13:50","playername":"Adam Hall","p1name":"Adam Hall","pid2":8471233,"pid1":8467925},{"altVideo":"http://h264.nhl.com/20102011/02/0658/2_658_njd_tbl_1011_a_discrete_T.B825_hit_800K_16x9_1.mp4","sweater":"13","localtime":"8:58 PM","xcoord":93,"desc":"Pavel Kubina HIT on Vladimir Zharkov","teamid":14,"strength":701,"pid":8465210,"formalEventId":"T.B825","period":2,"type":"Hit","p3name":"","eventid":825,"p2name":"Vladimir Zharkov","ycoord":28,"pid3":"","time":"14:03","playername":"Pavel Kubina","p1name":"Pavel Kubina","video":"2_658_njd_tbl_1011_h_discrete_T.B825_hit_800K_16x9_2.flv","pid2":8473592,"pid1":8465210},{"sweater":"5","localtime":"8:59 PM","xcoord":-31,"desc":"Colin White HIT on Dana Tyrell","teamid":1,"strength":701,"pid":8465005,"formalEventId":"T.B826","period":2,"type":"Hit","p3name":"","eventid":826,"p2name":"Dana Tyrell","ycoord":35,"pid3":"","time":"14:36","playername":"Colin White","p1name":"Colin White","pid2":8474095,"pid1":8465005},{"sweater":"26","altVideo":"http://h264.nhl.com/20102011/02/0658/2_658_njd_tbl_1011_a_discrete_T.B858_goal_800K_16x9_1.mp4","desc":"Martin St Louis GOAL on Martin Brodeur","g_shotType":"Backhand","formalEventId":"T.B858","type":"Goal","eventid":858,"g_totes":19,"p2name":"Martin Brodeur","time":"14:55","g_goalie":"Brodeur, M.","video":"2_658_njd_tbl_1011_a_discrete_T.B858_goal_800K_16x9_1.flv","g_ass2totes":14,"localtime":"8:59 PM","assists":"S. Stamkos (27), V. Hedman (14)","teamid":14,"xcoord":-73,"strength":701,"g_goalieID":8455710,"pid":8466378,"period":2,"g_ass1totes":27,"p3name":"Victor Hedman","pid3":8475167,"ycoord":3,"playername":"Martin St Louis","p1name":"Martin St Louis","pid2":8455710,"pid1":8466378},{"sweater":"91","localtime":"9:04 PM","xcoord":-61,"desc":"Steven Stamkos HIT on Andy Greene","teamid":14,"strength":701,"pid":8474564,"formalEventId":"T.B828","period":2,"type":"Hit","p3name":"","eventid":828,"p2name":"Andy Greene","ycoord":-34,"pid3":"","time":"16:32","playername":"Steven Stamkos","p1name":"Steven Stamkos","pid2":8472382,"pid1":8474564},{"altVideo":"http://h264.nhl.com/20102011/02/0658/2_658_njd_tbl_1011_a_discrete_T.B862_save_800K_16x9_1.mp4","sweater":"91","localtime":"9:04 PM","xcoord":-55,"desc":"Steven Stamkos SHOT on Martin Brodeur","teamid":14,"strength":701,"pid":8474564,"formalEventId":"T.B862","period":2,"type":"Shot","p3name":"","eventid":862,"p2name":"Martin Brodeur","ycoord":1,"pid3":"","time":"17:07","playername":"Steven Stamkos","p1name":"Steven Stamkos","video":"2_658_njd_tbl_1011_a_discrete_T.B862_save_800K_16x9_1.flv","pid2":8455710,"pid1":8474564},{"sweater":"5","localtime":"9:04 PM","xcoord":-88,"desc":"Colin White HIT on Pavel Kubina","teamid":1,"strength":701,"pid":8465005,"formalEventId":"T.B829","period":2,"type":"Hit","p3name":"","eventid":829,"p2name":"Pavel Kubina","ycoord":29,"pid3":"","time":"17:17","playername":"Colin White","p1name":"Colin White","pid2":8465210,"pid1":8465005},{"sweater":"23","localtime":"9:06 PM","xcoord":55,"desc":"David Clarkson SHOT on Dan Ellis","teamid":1,"strength":701,"pid":8470920,"formalEventId":"T.B865","period":2,"type":"Shot","p3name":"","eventid":865,"p2name":"Dan Ellis","ycoord":-29,"pid3":"","time":"18:25","playername":"David Clarkson","p1name":"David Clarkson","pid2":8468540,"pid1":8470920},{"sweater":"25","localtime":"9:08 PM","xcoord":34,"desc":"Jason Arnott SHOT on Dan Ellis","teamid":1,"strength":701,"pid":8459429,"formalEventId":"T.B868","period":2,"type":"Shot","p3name":"","eventid":868,"p2name":"Dan Ellis","ycoord":-25,"pid3":"","time":"19:59","playername":"Jason Arnott","p1name":"Jason Arnott","pid2":8468540,"pid1":8459429},{"sweater":"5","localtime":"9:26 PM","xcoord":-84,"desc":"Mattias Ohlund HI-STICKING on Nick Palmieri","teamid":14,"strength":703,"pid":8460503,"formalEventId":"T.B835","period":3,"type":"Penalty","p3name":"","eventid":835,"p2name":"Nick Palmieri","ycoord":36,"pid3":"","time":"00:34","playername":"Mattias Ohlund","p1name":"Mattias Ohlund","pid2":8473999,"pid1":8460503},{"altVideo":"http://h264.nhl.com/20102011/02/0658/2_658_njd_tbl_1011_a_discrete_T.B880_save_800K_16x9_1.mp4","sweater":"25","localtime":"9:28 PM","xcoord":-63,"desc":"Jason Arnott SHOT on Dan Ellis","teamid":1,"strength":702,"pid":8459429,"formalEventId":"T.B880","period":3,"type":"Shot","p3name":"","eventid":880,"p2name":"Dan Ellis","ycoord":6,"pid3":"","time":"01:27","playername":"Jason Arnott","p1name":"Jason Arnott","video":"2_658_njd_tbl_1011_a_discrete_T.B880_save_800K_16x9_1.flv","pid2":8468540,"pid1":8459429},{"altVideo":"http://h264.nhl.com/20102011/02/0658/2_658_njd_tbl_1011_a_discrete_T.B881_save_800K_16x9_1.mp4","sweater":"26","localtime":"9:28 PM","xcoord":-61,"desc":"Patrik Elias SHOT on Dan Ellis","teamid":1,"strength":702,"pid":8460542,"formalEventId":"T.B881","period":3,"type":"Shot","p3name":"","eventid":881,"p2name":"Dan Ellis","ycoord":25,"pid3":"","time":"01:42","playername":"Patrik Elias","p1name":"Patrik Elias","video":"2_658_njd_tbl_1011_a_discrete_T.B881_save_800K_16x9_1.flv","pid2":8468540,"pid1":8460542},{"sweater":"18","localtime":"9:29 PM","xcoord":45,"desc":"Adam Hall SHOT on Martin Brodeur","teamid":14,"strength":703,"pid":8467925,"formalEventId":"T.B883","period":3,"type":"Shot","p3name":"","eventid":883,"p2name":"Martin Brodeur","ycoord":-36,"pid3":"","time":"02:02","playername":"Adam Hall","p1name":"Adam Hall","pid2":8455710,"pid1":8467925},{"sweater":"19","localtime":"9:33 PM","xcoord":8,"desc":"Dominic Moore HIT on Ilya Kovalchuk","teamid":14,"strength":701,"pid":8468575,"formalEventId":"T.B844","period":3,"type":"Hit","p3name":"","eventid":844,"p2name":"Ilya Kovalchuk","ycoord":25,"pid3":"","time":"04:51","playername":"Dominic Moore","p1name":"Dominic Moore","pid2":8469454,"pid1":8468575},{"altVideo":"http://h264.nhl.com/20102011/02/0658/2_658_njd_tbl_1011_a_discrete_T.B889_save_800K_16x9_1.mp4","sweater":"18","localtime":"9:34 PM","xcoord":-59,"desc":"Vladimir Zharkov SHOT on Dan Ellis","teamid":1,"strength":701,"pid":8473592,"formalEventId":"T.B889","period":3,"type":"Shot","p3name":"","eventid":889,"p2name":"Dan Ellis","ycoord":13,"pid3":"","time":"05:27","playername":"Vladimir Zharkov","p1name":"Vladimir Zharkov","video":"2_658_njd_tbl_1011_a_discrete_T.B889_save_800K_16x9_1.flv","pid2":8468540,"pid1":8473592},{"sweater":"5","localtime":"9:36 PM","xcoord":89,"desc":"Colin White HIT on Vincent Lecavalier","teamid":1,"strength":701,"pid":8465005,"formalEventId":"T.B848","period":3,"type":"Hit","p3name":"","eventid":848,"p2name":"Vincent Lecavalier","ycoord":-26,"pid3":"","time":"07:46","playername":"Colin White","p1name":"Colin White","pid2":8467329,"pid1":8465005},{"sweater":"18","localtime":"9:36 PM","xcoord":-49,"desc":"Adam Hall HIT on Tim Sestito","teamid":14,"strength":701,"pid":8467925,"formalEventId":"T.B850","period":3,"type":"Hit","p3name":"","eventid":850,"p2name":"Tim Sestito","ycoord":32,"pid3":"","time":"08:01","playername":"Adam Hall","p1name":"Adam Hall","pid2":8471636,"pid1":8467925},{"altVideo":"http://h264.nhl.com/20102011/02/0658/2_658_njd_tbl_1011_a_discrete_T.B894_save_800K_16x9_1.mp4","sweater":"6","localtime":"9:37 PM","xcoord":73,"desc":"Ryan Malone SHOT on Martin Brodeur","teamid":14,"strength":701,"pid":8467988,"formalEventId":"T.B894","period":3,"type":"Shot","p3name":"","eventid":894,"p2name":"Martin Brodeur","ycoord":4,"pid3":"","time":"08:15","playername":"Ryan Malone","p1name":"Ryan Malone","video":"2_658_njd_tbl_1011_a_discrete_T.B894_save_800K_16x9_1.flv","pid2":8455710,"pid1":8467988},{"sweater":"18","localtime":"9:37 PM","xcoord":73,"desc":"Adam Hall SHOT on Martin Brodeur","teamid":14,"strength":701,"pid":8467925,"formalEventId":"T.B895","period":3,"type":"Shot","p3name":"","eventid":895,"p2name":"Martin Brodeur","ycoord":3,"pid3":"","time":"08:14","playername":"Adam Hall","p1name":"Adam Hall","pid2":8455710,"pid1":8467925},{"sweater":"6","localtime":"9:39 PM","xcoord":51,"desc":"Ryan Malone SHOT on Martin Brodeur","teamid":14,"strength":701,"pid":8467988,"formalEventId":"T.B897","period":3,"type":"Shot","p3name":"","eventid":897,"p2name":"Martin Brodeur","ycoord":-24,"pid3":"","time":"08:19","playername":"Ryan Malone","p1name":"Ryan Malone","pid2":8455710,"pid1":8467988},{"sweater":"44","localtime":"9:40 PM","xcoord":78,"desc":"Nate Thompson SHOT on Martin Brodeur","teamid":14,"strength":701,"pid":8470775,"formalEventId":"T.B899","period":3,"type":"Shot","p3name":"","eventid":899,"p2name":"Martin Brodeur","ycoord":7,"pid3":"","time":"09:23","playername":"Nate Thompson","p1name":"Nate Thompson","pid2":8455710,"pid1":8470775},{"sweater":"2","localtime":"9:41 PM","xcoord":62,"desc":"Mark Fraser HIT on Teddy Purcell","teamid":1,"strength":701,"pid":8471748,"formalEventId":"T.B955","period":3,"type":"Hit","p3name":"","eventid":955,"p2name":"Teddy Purcell","ycoord":36,"pid3":"","time":"09:43","playername":"Mark Fraser","p1name":"Mark Fraser","pid2":8473962,"pid1":8471748},{"sweater":"6","localtime":"9:45 PM","xcoord":95,"desc":"Ryan Malone HIT on Mark Fayne","teamid":14,"strength":701,"pid":8467988,"formalEventId":"T.B958","period":3,"type":"Hit","p3name":"","eventid":958,"p2name":"Mark Fayne","ycoord":-5,"pid3":"","time":"11:38","playername":"Ryan Malone","p1name":"Ryan Malone","pid2":8471816,"pid1":8467988},{"altVideo":"http://h264.nhl.com/20102011/02/0658/2_658_njd_tbl_1011_a_discrete_T.B1003_save_800K_16x9_1.mp4","sweater":"6","localtime":"9:46 PM","xcoord":83,"desc":"Ryan Malone SHOT on Martin Brodeur","teamid":14,"strength":701,"pid":8467988,"formalEventId":"T.B1003","period":3,"type":"Shot","p3name":"","eventid":1003,"p2name":"Martin Brodeur","ycoord":-5,"pid3":"","time":"11:58","playername":"Ryan Malone","p1name":"Ryan Malone","video":"2_658_njd_tbl_1011_a_discrete_T.B1003_save_800K_16x9_1.flv","pid2":8455710,"pid1":8467988},{"sweater":"77","localtime":"9:46 PM","xcoord":58,"desc":"Victor Hedman SHOT on Martin Brodeur","teamid":14,"strength":701,"pid":8475167,"formalEventId":"T.B1004","period":3,"type":"Shot","p3name":"","eventid":1004,"p2name":"Martin Brodeur","ycoord":35,"pid3":"","time":"12:36","playername":"Victor Hedman","p1name":"Victor Hedman","pid2":8455710,"pid1":8475167},{"sweater":"17","altVideo":"http://h264.nhl.com/20102011/02/0658/2_658_njd_tbl_1011_a_discrete_T.B1007_goal_800K_16x9_1.mp4","desc":"Ilya Kovalchuk GOAL on Dan Ellis","g_shotType":"Wrist Shot","formalEventId":"T.B1007","type":"Goal","eventid":1007,"g_totes":12,"p2name":"Dan Ellis","time":"13:40","g_goalie":"Ellis, D.","video":"2_658_njd_tbl_1011_a_discrete_T.B1007_goal_800K_16x9_1.flv","localtime":"9:47 PM","assists":"Unassisted","teamid":1,"xcoord":-57,"strength":701,"g_goalieID":8468540,"pid":8469454,"period":3,"p3name":"","pid3":"","ycoord":0,"playername":"Ilya Kovalchuk","p1name":"Ilya Kovalchuk","pid2":8468540,"pid1":8469454},{"sweater":"5","localtime":"9:49 PM","xcoord":47,"desc":"Colin White HIT on Steven Stamkos","teamid":1,"strength":701,"pid":8465005,"formalEventId":"T.B962","period":3,"type":"Hit","p3name":"","eventid":962,"p2name":"Steven Stamkos","ycoord":-35,"pid3":"","time":"14:14","playername":"Colin White","p1name":"Colin White","pid2":8474564,"pid1":8465005},{"sweater":"91","localtime":"9:49 PM","xcoord":90,"desc":"Steven Stamkos HIT on Andy Greene","teamid":14,"strength":701,"pid":8474564,"formalEventId":"T.B963","period":3,"type":"Hit","p3name":"","eventid":963,"p2name":"Andy Greene","ycoord":-20,"pid3":"","time":"14:21","playername":"Steven Stamkos","p1name":"Steven Stamkos","pid2":8472382,"pid1":8474564},{"sweater":"2","localtime":"9:49 PM","xcoord":-34,"desc":"Mark Fraser SHOT on Dan Ellis","teamid":1,"strength":701,"pid":8471748,"formalEventId":"T.B1009","period":3,"type":"Shot","p3name":"","eventid":1009,"p2name":"Dan Ellis","ycoord":-15,"pid3":"","time":"14:50","playername":"Mark Fraser","p1name":"Mark Fraser","pid2":8468540,"pid1":8471748},{"sweater":"4","localtime":"9:50 PM","xcoord":56,"desc":"Vincent Lecavalier SHOT on Martin Brodeur","teamid":14,"strength":701,"pid":8467329,"formalEventId":"T.B1011","period":3,"type":"Shot","p3name":"","eventid":1011,"p2name":"Martin Brodeur","ycoord":7,"pid3":"","time":"15:36","playername":"Vincent Lecavalier","p1name":"Vincent Lecavalier","pid2":8455710,"pid1":8467329},{"sweater":"8","localtime":"9:54 PM","xcoord":-92,"desc":"Dainius Zubrus HIT on Brett Clark","teamid":1,"strength":701,"pid":8464977,"formalEventId":"T.B967","period":3,"type":"Hit","p3name":"","eventid":967,"p2name":"Brett Clark","ycoord":18,"pid3":"","time":"16:49","playername":"Dainius Zubrus","p1name":"Dainius Zubrus","pid2":8465122,"pid1":8464977},{"sweater":"91","localtime":"9:54 PM","xcoord":89,"desc":"Steven Stamkos HIT on Mark Fayne","teamid":14,"strength":701,"pid":8474564,"formalEventId":"T.B968","period":3,"type":"Hit","p3name":"","eventid":968,"p2name":"Mark Fayne","ycoord":31,"pid3":"","time":"17:11","playername":"Steven Stamkos","p1name":"Steven Stamkos","pid2":8471816,"pid1":8474564},{"sweater":"12","localtime":"9:55 PM","xcoord":42,"desc":"Simon Gagne SHOT on Martin Brodeur","teamid":14,"strength":701,"pid":8467346,"formalEventId":"T.B1015","period":3,"type":"Shot","p3name":"","eventid":1015,"p2name":"Martin Brodeur","ycoord":1,"pid3":"","time":"17:39","playername":"Simon Gagne","p1name":"Simon Gagne","pid2":8455710,"pid1":8467346},{"sweater":"16","localtime":"9:56 PM","xcoord":52,"desc":"Teddy Purcell SHOT on Martin Brodeur","teamid":14,"strength":701,"pid":8473962,"formalEventId":"T.B1017","period":3,"type":"Shot","p3name":"","eventid":1017,"p2name":"Martin Brodeur","ycoord":11,"pid3":"","time":"18:28","playername":"Teddy Purcell","p1name":"Teddy Purcell","pid2":8455710,"pid1":8473962},{"sweater":"77","localtime":"9:56 PM","xcoord":95,"desc":"Victor Hedman HIT on Henrik Tallinder","teamid":14,"strength":701,"pid":8475167,"formalEventId":"T.B970","period":3,"type":"Hit","p3name":"","eventid":970,"p2name":"Henrik Tallinder","ycoord":-1,"pid3":"","time":"18:57","playername":"Victor Hedman","p1name":"Victor Hedman","pid2":8466182,"pid1":8475167},{"sweater":"7","localtime":"9:57 PM","xcoord":29,"desc":"Brett Clark SHOT on Martin Brodeur","teamid":14,"strength":701,"pid":8465122,"formalEventId":"T.B1019","period":3,"type":"Shot","p3name":"","eventid":1019,"p2name":"Martin Brodeur","ycoord":-15,"pid3":"","time":"19:31","playername":"Brett Clark","p1name":"Brett Clark","pid2":8455710,"pid1":8465122},{"sweater":"23","localtime":"9:57 PM","xcoord":-62,"desc":"David Clarkson SHOT on Dan Ellis","teamid":1,"strength":701,"pid":8470920,"formalEventId":"T.B1020","period":3,"type":"Shot","p3name":"","eventid":1020,"p2name":"Dan Ellis","ycoord":-10,"pid3":"","time":"19:48","playername":"David Clarkson","p1name":"David Clarkson","pid2":8468540,"pid1":8470920},{"sweater":"4","localtime":"9:57 PM","xcoord":46,"desc":"Vincent Lecavalier SHOT on Martin Brodeur","teamid":14,"strength":701,"pid":8467329,"formalEventId":"T.B1021","period":3,"type":"Shot","p3name":"","eventid":1021,"p2name":"Martin Brodeur","ycoord":-19,"pid3":"","time":"19:58","playername":"Vincent Lecavalier","p1name":"Vincent Lecavalier","pid2":8455710,"pid1":8467329}]},"awayteamnick":"Devils","hometeamnick":"Lightning","hometeamid":14}}}
